alibabacloud_viapi_regen20211119/__init__.py
alibabacloud_viapi_regen20211119/client.py
alibabacloud_viapi_regen20211119/models.py
alibabacloud_viapi_regen20211119-1.0.7.dist-info/LICENSE
alibabacloud_viapi_regen20211119-1.0.7.dist-info/METADATA
alibabacloud_viapi_regen20211119-1.0.7.dist-info/WHEEL
alibabacloud_viapi_regen20211119-1.0.7.dist-info/top_level.txt
alibabacloud_viapi_regen20211119-1.0.7.dist-info/RECORD
